AUTHORS.rst
CHANGES.rst
LICENSE.txt
MANIFEST.in
README.md
TODO.rst
setup.cfg
setup.py
croppic/__init__.py
croppic/admin.py
croppic/conf.py
croppic/forms.py
croppic/models.py
croppic/tests.py
croppic/urls.py
croppic/utils.py
croppic/views.py
croppic/static/croppic/css/croppic.css
croppic/static/croppic/img/cropperIcons.png
croppic/static/croppic/img/downloadIcon.png
croppic/static/croppic/img/headerBg.jpg
croppic/static/croppic/img/jobotic.png
croppic/static/croppic/img/jobotic_bubble.png
croppic/static/croppic/img/logo.png
croppic/static/croppic/img/night.jpg
croppic/static/croppic/img/placeholder.png
croppic/static/croppic/img/steinlinconsulting.png
croppic/static/croppic/img/studio42.png
croppic/static/croppic/js/croppic.js
croppic/static/croppic/js/croppic.min.js
django_croppic.egg-info/PKG-INFO
django_croppic.egg-info/SOURCES.txt
django_croppic.egg-info/dependency_links.txt
django_croppic.egg-info/not-zip-safe
django_croppic.egg-info/requires.txt
django_croppic.egg-info/top_level.txt